snoozin/__init__.py
snoozin/snoozin.py
snoozin/gmail/__init__.py
snoozin/gmail/creds.py
snoozin/gmail/read_email.py
snoozin/gmail/send_email.py
snoozingmail/__init__.py
snoozingmail/snoozin.py
snoozingmail/gmail/__init__.py
snoozingmail/gmail/creds.py
snoozingmail/gmail/modify.py
snoozingmail/gmail/read.py
snoozingmail/gmail/send.py
snoozingmail-0.0.7.dist-info/LICENSE
snoozingmail-0.0.7.dist-info/METADATA
snoozingmail-0.0.7.dist-info/WHEEL
snoozingmail-0.0.7.dist-info/top_level.txt
snoozingmail-0.0.7.dist-info/RECORD
