Metadata-Version: 2.1
Name: snoozingmail
Version: 0.0.7
Summary: A minimal python3 wrapper for the Gmail API
Home-page: https://github.com/nknaian/snoozingmail
Author: Nick Is Snoozin
Author-email: snoozinforabrusin@gmail.com
License: UNKNOWN
Platform: UNKNOWN
Classifier: Programming Language :: Python :: 3
Classifier: License :: OSI Approved :: MIT License
Requires-Python: >=3.6
Requires-Dist: google-api-python-client
Requires-Dist: google-auth-httplib2
Requires-Dist: google-auth-oauthlib
Requires-Dist: html2text
